aliyunsdkmaxcompute/__init__.py
aliyunsdkmaxcompute/endpoint.py
aliyunsdkmaxcompute/request/__init__.py
aliyunsdkmaxcompute/request/v20220104/CreatePackageRequest.py
aliyunsdkmaxcompute/request/v20220104/CreateProjectRequest.py
aliyunsdkmaxcompute/request/v20220104/CreateQuotaPlanRequest.py
aliyunsdkmaxcompute/request/v20220104/CreateQuotaScheduleRequest.py
aliyunsdkmaxcompute/request/v20220104/CreateRoleRequest.py
aliyunsdkmaxcompute/request/v20220104/DeleteQuotaPlanRequest.py
aliyunsdkmaxcompute/request/v20220104/GetJobResourceUsageRequest.py
aliyunsdkmaxcompute/request/v20220104/GetPackageRequest.py
aliyunsdkmaxcompute/request/v20220104/GetProjectRequest.py
aliyunsdkmaxcompute/request/v20220104/GetQuotaPlanRequest.py
aliyunsdkmaxcompute/request/v20220104/GetQuotaRequest.py
aliyunsdkmaxcompute/request/v20220104/GetQuotaScheduleRequest.py
aliyunsdkmaxcompute/request/v20220104/GetRoleAclOnObjectRequest.py
aliyunsdkmaxcompute/request/v20220104/GetRoleAclRequest.py
aliyunsdkmaxcompute/request/v20220104/GetRolePolicyRequest.py
aliyunsdkmaxcompute/request/v20220104/GetRunningJobsRequest.py
aliyunsdkmaxcompute/request/v20220104/GetTrustedProjectsRequest.py
aliyunsdkmaxcompute/request/v20220104/KillJobsRequest.py
aliyunsdkmaxcompute/request/v20220104/ListFunctionsRequest.py
aliyunsdkmaxcompute/request/v20220104/ListPackagesRequest.py
aliyunsdkmaxcompute/request/v20220104/ListProjectUsersRequest.py
aliyunsdkmaxcompute/request/v20220104/ListProjectsRequest.py
aliyunsdkmaxcompute/request/v20220104/ListQuotasPlansRequest.py
aliyunsdkmaxcompute/request/v20220104/ListQuotasRequest.py
aliyunsdkmaxcompute/request/v20220104/ListResourcesRequest.py
aliyunsdkmaxcompute/request/v20220104/ListRolesRequest.py
aliyunsdkmaxcompute/request/v20220104/ListTablesRequest.py
aliyunsdkmaxcompute/request/v20220104/ListUsersByRoleRequest.py
aliyunsdkmaxcompute/request/v20220104/ListUsersRequest.py
aliyunsdkmaxcompute/request/v20220104/UpdatePackageRequest.py
aliyun_python_sdk_maxcompute-1.0.3.dist-info/LICENSE
aliyun_python_sdk_maxcompute-1.0.3.dist-info/METADATA
aliyun_python_sdk_maxcompute-1.0.3.dist-info/WHEEL
aliyun_python_sdk_maxcompute-1.0.3.dist-info/top_level.txt
aliyun_python_sdk_maxcompute-1.0.3.dist-info/RECORD
